extras/__init__.py
extras/error_handler.py
extras/__pycache__/__init__.cpython-312.pyc
extras/__pycache__/error_handler.cpython-312.pyc
waymap-7.2.0.dist-info/licenses/LICENSE
waymap-7.2.0.dist-info/METADATA
waymap-7.2.0.dist-info/WHEEL
waymap-7.2.0.dist-info/entry_points.txt
waymap-7.2.0.dist-info/top_level.txt
waymap-7.2.0.dist-info/RECORD
