Metadata-Version: 2.4
Name: waymap
Version: 7.2.0
Summary: Advanced Web Application Security Scanner
Home-page: https://github.com/TrixSec/waymap
Author: Trix Cyrus
Author-email: trixsec@proton.me
Project-URL: Bug Reports, https://github.com/TrixSec/waymap/issues
Project-URL: Source, https://github.com/TrixSec/waymap
Project-URL: Documentation, https://github.com/TrixSec/waymap/blob/main/README.md
Keywords: security scanner vulnerability web-security penetration-testing
Classifier: Development Status :: 5 - Production/Stable
Classifier: Intended Audience :: Developers
Classifier: Intended Audience :: Information Technology
Classifier: Topic :: Security
Classifier: License :: OSI Approved :: GNU General Public License v3 (GPLv3)
Classifier: Programming Language :: Python :: 3
Classifier: Programming Language :: Python :: 3.8
Classifier: Programming Language :: Python :: 3.9
Classifier: Programming Language :: Python :: 3.10
Classifier: Programming Language :: Python :: 3.11
Classifier: Programming Language :: Python :: 3.12
Classifier: Operating System :: OS Independent
Requires-Python: >=3.8
License-File: LICENSE
Requires-Dist: requests>=2.31.0
Requires-Dist: beautifulsoup4>=4.12.0
Requires-Dist: colorama>=0.4.6
Requires-Dist: urllib3>=2.0.0
Requires-Dist: tqdm>=4.66.0
Requires-Dist: packaging>=23.0
Requires-Dist: fpdf>=1.7.2
Dynamic: author
Dynamic: author-email
Dynamic: classifier
Dynamic: description
Dynamic: description-content-type
Dynamic: home-page
Dynamic: keywords
Dynamic: license-file
Dynamic: project-url
Dynamic: requires-dist
Dynamic: requires-python
Dynamic: summary
